{"is_source_file": false, "format": "", "description": "", "external_files": [], "external_methods": [], "published": [], "classes": [], "methods": [], "calls": [], "search-terms": ["personal-notes-organizer", "README.md", "142185-142223"], "state": 2, "file_id": 1, "knowledge_revision": 17, "git_revision": "791d7c0378cdcadcb6b398e9590264c3ee1f8e67", "hash": "3581a644a01c48bcaa8fd96968bb24fc", "format-version": 4, "code-base-name": "notes_frontend", "filename": "README.md", "revision_history": [{"17": "791d7c0378cdcadcb6b398e9590264c3ee1f8e67"}]}